{"nodes": [{"id": "d_my_app_app_http_controllers_cbt_sesicontroller_php", "label": "SesiController.php", "file_type": "code", "source_file": "D:\\my-app\\app\\Http\\Controllers\\Cbt\\SesiController.php", "source_location": "L1"}, {"id": "cbt_sesicontroller_sesicontroller", "label": "SesiController", "file_type": "code", "source_file": "D:\\my-app\\app\\Http\\Controllers\\Cbt\\SesiController.php", "source_location": "L16"}, {"id": "cbt_sesicontroller_sesicontroller_index", "label": ".index()", "file_type": "code", "source_file": "D:\\my-app\\app\\Http\\Controllers\\Cbt\\SesiController.php", "source_location": "L21"}, {"id": "cbt_sesicontroller_sesicontroller_store", "label": ".store()", "file_type": "code", "source_file": "D:\\my-app\\app\\Http\\Controllers\\Cbt\\SesiController.php", "source_location": "L35"}, {"id": "cbt_sesicontroller_sesicontroller_update", "label": ".update()", "file_type": "code", "source_file": "D:\\my-app\\app\\Http\\Controllers\\Cbt\\SesiController.php", "source_location": "L45"}, {"id": "cbt_sesicontroller_sesicontroller_destroy", "label": ".destroy()", "file_type": "code", "source_file": "D:\\my-app\\app\\Http\\Controllers\\Cbt\\SesiController.php", "source_location": "L69"}], "edges": [{"source": "d_my_app_app_http_controllers_cbt_sesicontroller_php", "target": "controller", "relation": "imports", "context": "import", "confidence": "EXTRACTED", "source_file": "D:\\my-app\\app\\Http\\Controllers\\Cbt\\SesiController.php", "source_location": "L5", "weight": 1.0}, {"source": "d_my_app_app_http_controllers_cbt_sesicontroller_php", "target": "sesi", "relation": "imports", "context": "import", "confidence": "EXTRACTED", "source_file": "D:\\my-app\\app\\Http\\Controllers\\Cbt\\SesiController.php", "source_location": "L6", "weight": 1.0}, {"source": "d_my_app_app_http_controllers_cbt_sesicontroller_php", "target": "storesesirequest", "relation": "imports", "context": "import", "confidence": "EXTRACTED", "source_file": "D:\\my-app\\app\\Http\\Controllers\\Cbt\\SesiController.php", "source_location": "L7", "weight": 1.0}, {"source": "d_my_app_app_http_controllers_cbt_sesicontroller_php", "target": "updatesesirequest", "relation": "imports", "context": "import", "confidence": "EXTRACTED", "source_file": "D:\\my-app\\app\\Http\\Controllers\\Cbt\\SesiController.php", "source_location": "L8", "weight": 1.0}, {"source": "d_my_app_app_http_controllers_cbt_sesicontroller_php", "target": "sesiresource", "relation": "imports", "context": "import", "confidence": "EXTRACTED", "source_file": "D:\\my-app\\app\\Http\\Controllers\\Cbt\\SesiController.php", "source_location": "L9", "weight": 1.0}, {"source": "d_my_app_app_http_controllers_cbt_sesicontroller_php", "target": "gate", "relation": "imports", "context": "import", "confidence": "EXTRACTED", "source_file": "D:\\my-app\\app\\Http\\Controllers\\Cbt\\SesiController.php", "source_location": "L10", "weight": 1.0}, {"source": "d_my_app_app_http_controllers_cbt_sesicontroller_php", "target": "db", "relation": "imports", "context": "import", "confidence": "EXTRACTED", "source_file": "D:\\my-app\\app\\Http\\Controllers\\Cbt\\SesiController.php", "source_location": "L11", "weight": 1.0}, {"source": "d_my_app_app_http_controllers_cbt_sesicontroller_php", "target": "inertia", "relation": "imports", "context": "import", "confidence": "EXTRACTED", "source_file": "D:\\my-app\\app\\Http\\Controllers\\Cbt\\SesiController.php", "source_location": "L12", "weight": 1.0}, {"source": "d_my_app_app_http_controllers_cbt_sesicontroller_php", "target": "response", "relation": "imports", "context": "import", "confidence": "EXTRACTED", "source_file": "D:\\my-app\\app\\Http\\Controllers\\Cbt\\SesiController.php", "source_location": "L13", "weight": 1.0}, {"source": "d_my_app_app_http_controllers_cbt_sesicontroller_php", "target": "redirectresponse", "relation": "imports", "context": "import", "confidence": "EXTRACTED", "source_file": "D:\\my-app\\app\\Http\\Controllers\\Cbt\\SesiController.php", "source_location": "L14", "weight": 1.0}, {"source": "d_my_app_app_http_controllers_cbt_sesicontroller_php", "target": "cbt_sesicontroller_sesicontroller", "relation": "contains", "confidence": "EXTRACTED", "source_file": "D:\\my-app\\app\\Http\\Controllers\\Cbt\\SesiController.php", "source_location": "L16", "weight": 1.0}, {"source": "cbt_sesicontroller_sesicontroller", "target": "cbt_sesicontroller_sesicontroller_index", "relation": "method", "confidence": "EXTRACTED", "source_file": "D:\\my-app\\app\\Http\\Controllers\\Cbt\\SesiController.php", "source_location": "L21", "weight": 1.0}, {"source": "cbt_sesicontroller_sesicontroller", "target": "cbt_sesicontroller_sesicontroller_store", "relation": "method", "confidence": "EXTRACTED", "source_file": "D:\\my-app\\app\\Http\\Controllers\\Cbt\\SesiController.php", "source_location": "L35", "weight": 1.0}, {"source": "cbt_sesicontroller_sesicontroller", "target": "cbt_sesicontroller_sesicontroller_update", "relation": "method", "confidence": "EXTRACTED", "source_file": "D:\\my-app\\app\\Http\\Controllers\\Cbt\\SesiController.php", "source_location": "L45", "weight": 1.0}, {"source": "cbt_sesicontroller_sesicontroller", "target": "cbt_sesicontroller_sesicontroller_destroy", "relation": "method", "confidence": "EXTRACTED", "source_file": "D:\\my-app\\app\\Http\\Controllers\\Cbt\\SesiController.php", "source_location": "L69", "weight": 1.0}], "raw_calls": [{"caller_nid": "cbt_sesicontroller_sesicontroller_index", "callee": "Gate", "is_member_call": false, "source_file": "D:\\my-app\\app\\Http\\Controllers\\Cbt\\SesiController.php", "source_location": "L23"}, {"caller_nid": "cbt_sesicontroller_sesicontroller_index", "callee": "paginate", "is_member_call": true, "source_file": "D:\\my-app\\app\\Http\\Controllers\\Cbt\\SesiController.php", "source_location": "L25"}, {"caller_nid": "cbt_sesicontroller_sesicontroller_index", "callee": "Sesi", "is_member_call": false, "source_file": "D:\\my-app\\app\\Http\\Controllers\\Cbt\\SesiController.php", "source_location": "L25"}, {"caller_nid": "cbt_sesicontroller_sesicontroller_index", "callee": "Inertia", "is_member_call": false, "source_file": "D:\\my-app\\app\\Http\\Controllers\\Cbt\\SesiController.php", "source_location": "L27"}, {"caller_nid": "cbt_sesicontroller_sesicontroller_index", "callee": "SesiResource", "is_member_call": false, "source_file": "D:\\my-app\\app\\Http\\Controllers\\Cbt\\SesiController.php", "source_location": "L28"}, {"caller_nid": "cbt_sesicontroller_sesicontroller_store", "callee": "Sesi", "is_member_call": false, "source_file": "D:\\my-app\\app\\Http\\Controllers\\Cbt\\SesiController.php", "source_location": "L37"}, {"caller_nid": "cbt_sesicontroller_sesicontroller_store", "callee": "validated", "is_member_call": true, "source_file": "D:\\my-app\\app\\Http\\Controllers\\Cbt\\SesiController.php", "source_location": "L37"}, {"caller_nid": "cbt_sesicontroller_sesicontroller_store", "callee": "with", "is_member_call": true, "source_file": "D:\\my-app\\app\\Http\\Controllers\\Cbt\\SesiController.php", "source_location": "L39"}, {"caller_nid": "cbt_sesicontroller_sesicontroller_store", "callee": "back", "is_member_call": true, "source_file": "D:\\my-app\\app\\Http\\Controllers\\Cbt\\SesiController.php", "source_location": "L39"}, {"caller_nid": "cbt_sesicontroller_sesicontroller_store", "callee": "redirect", "is_member_call": false, "source_file": "D:\\my-app\\app\\Http\\Controllers\\Cbt\\SesiController.php", "source_location": "L39"}, {"caller_nid": "cbt_sesicontroller_sesicontroller_update", "callee": "boolean", "is_member_call": true, "source_file": "D:\\my-app\\app\\Http\\Controllers\\Cbt\\SesiController.php", "source_location": "L50"}, {"caller_nid": "cbt_sesicontroller_sesicontroller_update", "callee": "\\Illuminate\\Support\\Facades\\Schema", "is_member_call": false, "source_file": "D:\\my-app\\app\\Http\\Controllers\\Cbt\\SesiController.php", "source_location": "L51"}, {"caller_nid": "cbt_sesicontroller_sesicontroller_update", "callee": "exists", "is_member_call": true, "source_file": "D:\\my-app\\app\\Http\\Controllers\\Cbt\\SesiController.php", "source_location": "L52"}, {"caller_nid": "cbt_sesicontroller_sesicontroller_update", "callee": "where", "is_member_call": true, "source_file": "D:\\my-app\\app\\Http\\Controllers\\Cbt\\SesiController.php", "source_location": "L52"}, {"caller_nid": "cbt_sesicontroller_sesicontroller_update", "callee": "DB", "is_member_call": false, "source_file": "D:\\my-app\\app\\Http\\Controllers\\Cbt\\SesiController.php", "source_location": "L52"}, {"caller_nid": "cbt_sesicontroller_sesicontroller_update", "callee": "with", "is_member_call": true, "source_file": "D:\\my-app\\app\\Http\\Controllers\\Cbt\\SesiController.php", "source_location": "L54"}, {"caller_nid": "cbt_sesicontroller_sesicontroller_update", "callee": "back", "is_member_call": true, "source_file": "D:\\my-app\\app\\Http\\Controllers\\Cbt\\SesiController.php", "source_location": "L54"}, {"caller_nid": "cbt_sesicontroller_sesicontroller_update", "callee": "redirect", "is_member_call": false, "source_file": "D:\\my-app\\app\\Http\\Controllers\\Cbt\\SesiController.php", "source_location": "L54"}, {"caller_nid": "cbt_sesicontroller_sesicontroller_update", "callee": "validated", "is_member_call": true, "source_file": "D:\\my-app\\app\\Http\\Controllers\\Cbt\\SesiController.php", "source_location": "L59"}, {"caller_nid": "cbt_sesicontroller_sesicontroller_update", "callee": "boolean", "is_member_call": true, "source_file": "D:\\my-app\\app\\Http\\Controllers\\Cbt\\SesiController.php", "source_location": "L60"}, {"caller_nid": "cbt_sesicontroller_sesicontroller_update", "callee": "with", "is_member_call": true, "source_file": "D:\\my-app\\app\\Http\\Controllers\\Cbt\\SesiController.php", "source_location": "L63"}, {"caller_nid": "cbt_sesicontroller_sesicontroller_update", "callee": "back", "is_member_call": true, "source_file": "D:\\my-app\\app\\Http\\Controllers\\Cbt\\SesiController.php", "source_location": "L63"}, {"caller_nid": "cbt_sesicontroller_sesicontroller_update", "callee": "redirect", "is_member_call": false, "source_file": "D:\\my-app\\app\\Http\\Controllers\\Cbt\\SesiController.php", "source_location": "L63"}, {"caller_nid": "cbt_sesicontroller_sesicontroller_destroy", "callee": "Gate", "is_member_call": false, "source_file": "D:\\my-app\\app\\Http\\Controllers\\Cbt\\SesiController.php", "source_location": "L71"}, {"caller_nid": "cbt_sesicontroller_sesicontroller_destroy", "callee": "delete", "is_member_call": true, "source_file": "D:\\my-app\\app\\Http\\Controllers\\Cbt\\SesiController.php", "source_location": "L74"}, {"caller_nid": "cbt_sesicontroller_sesicontroller_destroy", "callee": "with", "is_member_call": true, "source_file": "D:\\my-app\\app\\Http\\Controllers\\Cbt\\SesiController.php", "source_location": "L75"}, {"caller_nid": "cbt_sesicontroller_sesicontroller_destroy", "callee": "back", "is_member_call": true, "source_file": "D:\\my-app\\app\\Http\\Controllers\\Cbt\\SesiController.php", "source_location": "L75"}, {"caller_nid": "cbt_sesicontroller_sesicontroller_destroy", "callee": "redirect", "is_member_call": false, "source_file": "D:\\my-app\\app\\Http\\Controllers\\Cbt\\SesiController.php", "source_location": "L75"}, {"caller_nid": "cbt_sesicontroller_sesicontroller_destroy", "callee": "with", "is_member_call": true, "source_file": "D:\\my-app\\app\\Http\\Controllers\\Cbt\\SesiController.php", "source_location": "L77"}, {"caller_nid": "cbt_sesicontroller_sesicontroller_destroy", "callee": "back", "is_member_call": true, "source_file": "D:\\my-app\\app\\Http\\Controllers\\Cbt\\SesiController.php", "source_location": "L77"}, {"caller_nid": "cbt_sesicontroller_sesicontroller_destroy", "callee": "redirect", "is_member_call": false, "source_file": "D:\\my-app\\app\\Http\\Controllers\\Cbt\\SesiController.php", "source_location": "L77"}]}